<Gesture Name="pigtail" Subject="1" Speed="medium" Number="1" NumPts="64" Milliseconds="0" AppName="Gestures" AppVer="3.5.0.0" Date="Friday, June 12, 2026" TimeOfDay="03:08:21 PM"><Point X="56" Y="190" T="0" /><Point X="63" Y="188" T="0" /><Point X="70" Y="186" T="0" /><Point X="77" Y="184" T="0" /><Point X="84" Y="181" T="0" /><Point X="90" Y="176" T="0" /><Point X="95" Y="171" T="0" /><Point X="101" Y="165" T="0" /><Point X="107" Y="161" T="0" /><Point X="113" Y="157" T="0" /><Point X="119" Y="152" T="0" /><Point X="126" Y="148" T="0" /><Point X="132" Y="145" T="0" /><Point X="138" Y="140" T="0" /><Point X="143" Y="134" T="0" /><Point X="147" Y="128" T="0" /><Point X="150" Y="121" T="0" /><Point X="152" Y="113" T="0" /><Point X="154" Y="106" T="0" /><Point X="156" Y="99" T="0" /><Point X="158" Y="91" T="0" /><Point X="160" Y="84" T="0" /><Point X="163" Y="77" T="0" /><Point X="164" Y="69" T="0" /><Point X="163" Y="62" T="0" /><Point X="160" Y="55" T="0" /><Point X="157" Y="48" T="0" /><Point X="153" Y="42" T="0" /><Point X="145" Y="40" T="0" /><Point X="138" Y="38" T="0" /><Point X="131" Y="36" T="0" /><Point X="123" Y="36" T="0" /><Point X="116" Y="36" T="0" /><Point X="108" Y="36" T="0" /><Point X="102" Y="41" T="0" /><Point X="99" Y="48" T="0" /><Point X="97" Y="55" T="0" /><Point X="96" Y="63" T="0" /><Point X="96" Y="70" T="0" /><Point X="95" Y="78" T="0" /><Point X="94" Y="85" T="0" /><Point X="93" Y="93" T="0" /><Point X="93" Y="101" T="0" /><Point X="96" Y="108" T="0" /><Point X="99" Y="114" T="0" /><Point X="103" Y="121" T="0" /><Point X="107" Y="127" T="0" /><Point X="112" Y="133" T="0" /><Point X="117" Y="139" T="0" /><Point X="122" Y="144" T="0" /><Point X="127" Y="150" T="0" /><Point X="131" Y="156" T="0" /><Point X="136" Y="162" T="0" /><Point X="141" Y="168" T="0" /><Point X="146" Y="173" T="0" /><Point X="152" Y="178" T="0" /><Point X="158" Y="183" T="0" /><Point X="165" Y="187" T="0" /><Point X="172" Y="189" T="0" /><Point X="179" Y="192" T="0" /><Point X="186" Y="194" T="0" /><Point X="193" Y="198" T="0" /><Point X="199" Y="202" T="0" /><Point X="203" Y="206" T="0" /></Gesture>